open_enum/LICENSE
open_enum/__init__.py
open_enum/open_enum.py
open_enum/open_enum_test.py
open_enum-0.1.0.dist-info/WHEEL
open_enum-0.1.0.dist-info/METADATA
open_enum-0.1.0.dist-info/RECORD
