Metadata-Version: 2.3
Name: open-enum
Version: 0.1.0
Summary: Add your description here
Requires-Python: >=3.12
